godspeed_api/__init__.py
godspeed_api/api.py
godspeed_api/Models/Attachment.py
godspeed_api/Models/Label.py
godspeed_api/Models/ListTasksResponse.py
godspeed_api/Models/Status.py
godspeed_api/Models/Task.py
godspeed_api/Models/TaskList.py
godspeed_api/Models/__init__.py
tests/__init__.py
tests/test_api.py
godspeed_api-0.2.2.dist-info/LICENSE
godspeed_api-0.2.2.dist-info/METADATA
godspeed_api-0.2.2.dist-info/WHEEL
godspeed_api-0.2.2.dist-info/top_level.txt
godspeed_api-0.2.2.dist-info/RECORD
