Metadata-Version: 2.1
Name: godspeed_api
Version: 0.2.2
Summary: A Godspeed task manager API wrapper
Author: Artem Trubacheev
Author-email: almaz5200@gmail.com
Keywords: python,godspeed
Classifier: Development Status :: 3 - Alpha
Classifier: Intended Audience :: Education
Classifier: Programming Language :: Python :: 2
Classifier: Programming Language :: Python :: 3
Classifier: Operating System :: MacOS :: MacOS X
Classifier: Operating System :: Microsoft :: Windows
License-File: LICENSE
Requires-Dist: requests
Requires-Dist: dacite
